zenv/__init__.py
zenv/cli.py
zenv/const.py
zenv/core.py
zenv/utils.py
zenv_cli-0.4.3.dist-info/entry_points.txt
zenv_cli-0.4.3.dist-info/LICENSE
zenv_cli-0.4.3.dist-info/WHEEL
zenv_cli-0.4.3.dist-info/METADATA
zenv_cli-0.4.3.dist-info/RECORD
