Metadata-Version: 2.1
Name: zenv-cli
Version: 0.4.3
Summary: 
Home-page: https://github.com/zueve/zenv
License: MIT
Keywords: cli,docker,developer,environment
Author: evegny.zuev
Author-email: zueves@gmail.com
Requires-Python: >=3.7,<4.0
Classifier: License :: OSI Approved :: MIT License
Classifier: Programming Language :: Python :: 3
Classifier: Programming Language :: Python :: 3.10
Classifier: Programming Language :: Python :: 3.7
Classifier: Programming Language :: Python :: 3.8
Classifier: Programming Language :: Python :: 3.9
Requires-Dist: click
Requires-Dist: toml (>=0.10.0,<0.11.0)
Project-URL: Documentation, https://github.com/zueve/zenv
Project-URL: Repository, https://github.com/zueve/zenv
